aqua_blue/__init__.py
aqua_blue/datetimelikearray.py
aqua_blue/models.py
aqua_blue/readouts.py
aqua_blue/reservoirs.py
aqua_blue/time_series.py
aqua_blue/utilities.py
aqua_blue-0.2.19.dist-info/METADATA
aqua_blue-0.2.19.dist-info/WHEEL
aqua_blue-0.2.19.dist-info/licenses/LICENSE
aqua_blue-0.2.19.dist-info/RECORD
