Metadata-Version: 2.4
Name: aqua-blue
Version: 0.2.19
Summary: Lightweight and basic reservoir computing library
Project-URL: Homepage, https://github.com/jwjeffr/aqua-blue
License-Expression: MIT
License-File: LICENSE
Keywords: computing,forecasting,learning,machine,prediction,reservoir,series,time
Classifier: Programming Language :: Python :: 3.9
Classifier: Programming Language :: Python :: 3.10
Classifier: Programming Language :: Python :: 3.11
Classifier: Programming Language :: Python :: 3.12
Requires-Python: >=3.9
Requires-Dist: numpy<2.2,>=2.0
Requires-Dist: python-dateutil~=2.9.0.post0
Requires-Dist: setuptools~=79.0.0
Requires-Dist: tzdata~=2025.1
Provides-Extra: dev
Requires-Dist: coverage~=7.8.0; extra == 'dev'
Requires-Dist: hatchling~=1.27.0; extra == 'dev'
Requires-Dist: mypy~=1.13.0; extra == 'dev'
Requires-Dist: pdoc~=15.0.1; extra == 'dev'
Requires-Dist: pytest~=8.0.2; extra == 'dev'
Requires-Dist: ruff~=0.9.4; extra == 'dev'
Requires-Dist: types-python-dateutil~=2.9.0.20241206; extra == 'dev'
Provides-Extra: examples
Requires-Dist: aqua-blue-hyperopt~=0.0.3; extra == 'examples'
Requires-Dist: matplotlib~=3.9.4; extra == 'examples'
Requires-Dist: requests~=2.32.3; extra == 'examples'
Requires-Dist: scikit-learn~=1.6.1; extra == 'examples'
Requires-Dist: scipy~=1.13.1; extra == 'examples'
Requires-Dist: torch~=2.7.0; extra == 'examples'
